{
    "keep": {
        "days": true,
        "amount": 14
    },
    "auditLog": "D:\\programming hero\\INTERSHIP\\Ronjit_course_vedio\\CourshVedio_server\\logger\\winston\\successes\\.11d66d819df440ad2808bfc9ffb58f3a133fae37-audit.json",
    "files": [
        {
            "date": 1695062512991,
            "name": "D:\\programming hero\\INTERSHIP\\Ronjit_course_vedio\\CourshVedio_server\\logger\\winston\\successes\\PHU-2023-09-19-00-success.log",
            "hash": "29c709e688f0b5f335dc112bcaf8535e6e5ac74930911607b91baa1692db291a"
        },
        {
            "date": 1695142333681,
            "name": "D:\\programming hero\\INTERSHIP\\Ronjit_course_vedio\\CourshVedio_server\\logger\\winston\\successes\\PHU-2023-09-19-22-success.log",
            "hash": "7863b933936f5f6e870fc03d803036158e752ba3854ca94dbbb90d6b4cef777c"
        },
        {
            "date": 1695145055466,
            "name": "D:\\programming hero\\INTERSHIP\\Ronjit_course_vedio\\CourshVedio_server\\logger\\winston\\successes\\PHU-2023-09-19-23-success.log",
            "hash": "bdde414bd11f3ca43ba3af814fba24164e2aceb33b7bac3f9e2c0824d1df69d3"
        },
        {
            "date": 1695146470706,
            "name": "D:\\programming hero\\INTERSHIP\\Ronjit_course_vedio\\CourshVedio_server\\logger\\winston\\successes\\PHU-2023-09-20-00-success.log",
            "hash": "64c51bdb6ad11c49d926df7739e0026fde049c294f9e0e57a05a37052fe1ab8c"
        },
        {
            "date": 1695151053931,
            "name": "D:\\programming hero\\INTERSHIP\\Ronjit_course_vedio\\CourshVedio_server\\logger\\winston\\successes\\PHU-2023-09-20-01-success.log",
            "hash": "3d90357b0b01aeaf6c8f422fadd381690e090892f3ce2d1e022ba8d89193ac55"
        },
        {
            "date": 1695190614392,
            "name": "D:\\programming hero\\INTERSHIP\\Ronjit_course_vedio\\CourshVedio_server\\logger\\winston\\successes\\PHU-2023-09-20-12-success.log",
            "hash": "d130ccdd5e448eeabf5f9a0e0e591b55bdf8914e1ea87e749aa72179681cbad4"
        },
        {
            "date": 1695197239649,
            "name": "D:\\programming hero\\INTERSHIP\\Ronjit_course_vedio\\CourshVedio_server\\logger\\winston\\successes\\PHU-2023-09-20-14-success.log",
            "hash": "5e418948beb9c6f54504e710c33a573ff04fcda9d9e4a1b71dd730ded93f7774"
        },
        {
            "date": 1695205981628,
            "name": "D:\\programming hero\\INTERSHIP\\Ronjit_course_vedio\\CourshVedio_server\\logger\\winston\\successes\\PHU-2023-09-20-16-success.log",
            "hash": "ac11ee943e77be01ec3e1fe80b736bb40c7610e27f1c1f3d3ed24fbd443eba24"
        },
        {
            "date": 1695208375399,
            "name": "D:\\programming hero\\INTERSHIP\\Ronjit_course_vedio\\CourshVedio_server\\logger\\winston\\successes\\PHU-2023-09-20-17-success.log",
            "hash": "334c8698c93a00b98a464158a748df23c9dcb6a8397d05efeac936122075f814"
        }
    ],
    "hashType": "sha256"
}